{
    "chart_title": "Experiencia de compra",
    "chart_subtitle": "Últimos 13 meses",
    "data": [
        {
            "title": "41 - Huechuraba",
            "values": [
                { "x": "Mar 17", "y": 14 },
                { "x": "Abr 17", "y": 26 },
                { "x": "May 17", "y": 12 },
                { "x": "Jun 17", "y": 11 },
                { "x": "Jul 17", "y": 10 }
            ]
        },
        {
            "title": "81 - Arica",
            "values": [
                { "x": "Mar 17", "y": 10 },
                { "x": "Abr 17", "y": 11 },
                { "x": "May 17", "y": 45.2 },
                { "x": "Jun 17", "y": 15.4 },
                { "x": "Jul 17", "y": 20 }
            ]
        }
    ]
}
